[
    {
        "puzzle_id": 18472,
        "promo_id": null,
        "version": 3,
        "puzzle_meta": {
            "formatType": "Normal",
            "publishType": "Daily",
            "title": "The Mini Crossword",
            "printDate": "2020-07-26",
            "printDotw": 0,
            "editor": "",
            "height": 5,
            "width": 5,
            "author": "Joel Fagliano"
        },
        "print_date": "2020-07-26",
        "enhanced_tier_date": null,
        "puzzle_data": {
            "clues": {
                "A": [
                    {
                        "clueStart": 0,
                        "clueNum": 1,
                        "clueEnd": 3,
                        "value": "Curse with bad luck"
                    },
                    {
                        "clueStart": 5,
                        "clueNum": 5,
                        "clueEnd": 9,
                        "value": "Zodiac sign between Pisces and Taurus"
                    },
                    {
                        "clueStart": 10,
                        "clueNum": 7,
                        "clueEnd": 14,
                        "value": "Staff assistant on \"The West Wing\""
                    },
                    {
                        "clueStart": 15,
                        "clueNum": 8,
                        "clueEnd": 19,
                        "value": "Take pleasure in"
                    },
                    {
                        "clueStart": 21,
                        "clueNum": 9,
                        "clueEnd": 24,
                        "value": "Without"
                    }
                ],
                "D": [
                    {
                        "clueStart": 0,
                        "clueNum": 1,
                        "clueEnd": 15,
                        "value": "Gemstone that starts with an 8-point Scrabble letter"
                    },
                    {
                        "clueStart": 1,
                        "clueNum": 2,
                        "clueEnd": 21,
                        "value": "Smooths out the wrinkles"
                    },
                    {
                        "clueStart": 2,
                        "clueNum": 3,
                        "clueEnd": 22,
                        "value": "Black-clad assassin"
                    },
                    {
                        "clueStart": 3,
                        "clueNum": 4,
                        "clueEnd": 23,
                        "value": "Chemical element that starts with an 8-point Scrabble letter"
                    },
                    {
                        "clueStart": 9,
                        "clueNum": 6,
                        "clueEnd": 24,
                        "value": "\"Survey ___ ...\" (\"Family Feud\" catchphrase)"
                    }
                ]
            },
            "answers": [
                "J",
                "I",
                "N",
                "X",
                null,
                "A",
                "R",
                "I",
                "E",
                "S",
                "D",
                "O",
                "N",
                "N",
                "A",
                "E",
                "N",
                "J",
                "O",
                "Y",
                null,
                "S",
                "A",
                "N",
                "S"
            ],
            "layout": [
                1,
                1,
                1,
                1,
                0,
                1,
                1,
                1,
                1,
                1,
                1,
                1,
                1,
                1,
                1,
                1,
                1,
                1,
                1,
                1,
                0,
                1,
                1,
                1,
                1
            ]
        }
    }
]