[
    {
        "puzzle_id": 20227,
        "promo_id": null,
        "version": 3,
        "puzzle_meta": {
            "formatType": "Normal",
            "publishType": "Daily",
            "title": "The Mini Crossword",
            "printDate": "2022-06-05",
            "printDotw": 0,
            "editor": "",
            "height": 5,
            "width": 5,
            "author": "Joel Fagliano"
        },
        "print_date": "2022-06-05",
        "enhanced_tier_date": null,
        "puzzle_data": {
            "clues": {
                "A": [
                    {
                        "clueStart": 1,
                        "clueNum": 1,
                        "clueEnd": 4,
                        "value": "Sound after \"Ah-ah-ah ...\""
                    },
                    {
                        "clueStart": 6,
                        "clueNum": 5,
                        "clueEnd": 9,
                        "value": "South ___ (area behind the White House)"
                    },
                    {
                        "clueStart": 10,
                        "clueNum": 6,
                        "clueEnd": 14,
                        "value": "Cryptocurrency units"
                    },
                    {
                        "clueStart": 15,
                        "clueNum": 7,
                        "clueEnd": 18,
                        "value": "University in Durham, N.C."
                    },
                    {
                        "clueStart": 20,
                        "clueNum": 8,
                        "clueEnd": 23,
                        "value": "Good-looking guy"
                    }
                ],
                "D": [
                    {
                        "clueStart": 1,
                        "clueNum": 1,
                        "clueEnd": 21,
                        "value": "Social influence"
                    },
                    {
                        "clueStart": 2,
                        "clueNum": 2,
                        "clueEnd": 22,
                        "value": "Poem with a 5/7/5 pattern"
                    },
                    {
                        "clueStart": 3,
                        "clueNum": 3,
                        "clueEnd": 23,
                        "value": "Had the rights to"
                    },
                    {
                        "clueStart": 4,
                        "clueNum": 4,
                        "clueEnd": 14,
                        "value": "Run-___ (long sentences)"
                    },
                    {
                        "clueStart": 10,
                        "clueNum": 6,
                        "clueEnd": 20,
                        "value": "Music collectibles, for short"
                    }
                ]
            },
            "answers": [
                null,
                "C",
                "H",
                "O",
                "O",
                null,
                "L",
                "A",
                "W",
                "N",
                "C",
                "O",
                "I",
                "N",
                "S",
                "D",
                "U",
                "K",
                "E",
                null,
                "S",
                "T",
                "U",
                "D",
                null
            ],
            "layout": [
                0,
                1,
                1,
                1,
                1,
                0,
                1,
                1,
                1,
                1,
                1,
                1,
                1,
                1,
                1,
                1,
                1,
                1,
                1,
                0,
                1,
                1,
                1,
                1,
                0
            ]
        }
    }
]