[
    {
        "puzzle_id": 22282,
        "promo_id": null,
        "version": 3,
        "puzzle_meta": {
            "formatType": "Normal",
            "publishType": "Daily",
            "title": "The Mini Crossword",
            "printDate": "2024-10-04",
            "printDotw": 0,
            "editor": "Sam Ezersky",
            "height": 5,
            "width": 5,
            "author": "Wyna Liu"
        },
        "print_date": "2024-10-04",
        "enhanced_tier_date": null,
        "puzzle_data": {
            "clues": {
                "A": [
                    {
                        "clueStart": 1,
                        "clueNum": 1,
                        "clueEnd": 4,
                        "value": "What lanternfish can do, using organs called photophores"
                    },
                    {
                        "clueStart": 5,
                        "clueNum": 5,
                        "clueEnd": 9,
                        "value": "Channel with \"Vanderpump Rules\" and \"Below Deck\""
                    },
                    {
                        "clueStart": 10,
                        "clueNum": 6,
                        "clueEnd": 14,
                        "value": "Consumed"
                    },
                    {
                        "clueStart": 15,
                        "clueNum": 7,
                        "clueEnd": 19,
                        "value": "Really need a bath"
                    },
                    {
                        "clueStart": 20,
                        "clueNum": 8,
                        "clueEnd": 23,
                        "value": "Change for a twenty"
                    }
                ],
                "D": [
                    {
                        "clueStart": 1,
                        "clueNum": 1,
                        "clueEnd": 21,
                        "value": "Storm drain cover"
                    },
                    {
                        "clueStart": 2,
                        "clueNum": 2,
                        "clueEnd": 22,
                        "value": "\"Et tu, Brute?\" language"
                    },
                    {
                        "clueStart": 3,
                        "clueNum": 3,
                        "clueEnd": 23,
                        "value": "Bakery fixtures"
                    },
                    {
                        "clueStart": 4,
                        "clueNum": 4,
                        "clueEnd": 19,
                        "value": "Stats or policy nerd"
                    },
                    {
                        "clueStart": 5,
                        "clueNum": 5,
                        "clueEnd": 20,
                        "value": "Work email sign-off"
                    }
                ]
            },
            "answers": [
                null,
                "G",
                "L",
                "O",
                "W",
                "B",
                "R",
                "A",
                "V",
                "O",
                "E",
                "A",
                "T",
                "E",
                "N",
                "S",
                "T",
                "I",
                "N",
                "K",
                "T",
                "E",
                "N",
                "S",
                null
            ],
            "layout": [
                0,
                1,
                1,
                1,
                1,
                1,
                1,
                1,
                1,
                1,
                1,
                1,
                1,
                1,
                1,
                1,
                1,
                1,
                1,
                1,
                1,
                1,
                1,
                1,
                0
            ]
        }
    }
]