[
    {
        "puzzle_id": 21681,
        "promo_id": null,
        "version": 3,
        "puzzle_meta": {
            "formatType": "Normal",
            "publishType": "Daily",
            "title": "The Mini Crossword",
            "printDate": "2024-01-14",
            "printDotw": 0,
            "editor": "",
            "height": 5,
            "width": 5,
            "author": "Joel Fagliano"
        },
        "print_date": "2024-01-14",
        "enhanced_tier_date": null,
        "puzzle_data": {
            "clues": {
                "A": [
                    {
                        "clueStart": 1,
                        "clueNum": 1,
                        "clueEnd": 3,
                        "value": "T.S.A. ___Check"
                    },
                    {
                        "clueStart": 5,
                        "clueNum": 4,
                        "clueEnd": 9,
                        "value": "Basketball infractions"
                    },
                    {
                        "clueStart": 10,
                        "clueNum": 6,
                        "clueEnd": 14,
                        "value": "Tech company with a food name (that's headed by a Cook)"
                    },
                    {
                        "clueStart": 15,
                        "clueNum": 7,
                        "clueEnd": 19,
                        "value": "It made Mercury a star"
                    },
                    {
                        "clueStart": 20,
                        "clueNum": 8,
                        "clueEnd": 24,
                        "value": "Use money"
                    }
                ],
                "D": [
                    {
                        "clueStart": 1,
                        "clueNum": 1,
                        "clueEnd": 21,
                        "value": "Window that's opened automatically"
                    },
                    {
                        "clueStart": 2,
                        "clueNum": 2,
                        "clueEnd": 22,
                        "value": "Currency of India"
                    },
                    {
                        "clueStart": 3,
                        "clueNum": 3,
                        "clueEnd": 23,
                        "value": "Actress Pompeo of \"Grey's Anatomy\""
                    },
                    {
                        "clueStart": 5,
                        "clueNum": 4,
                        "clueEnd": 20,
                        "value": "Common queries, for short"
                    },
                    {
                        "clueStart": 9,
                        "clueNum": 5,
                        "clueEnd": 24,
                        "value": "Schedule ___ (email function)"
                    }
                ]
            },
            "answers": [
                null,
                "P",
                "R",
                "E",
                null,
                "F",
                "O",
                "U",
                "L",
                "S",
                "A",
                "P",
                "P",
                "L",
                "E",
                "Q",
                "U",
                "E",
                "E",
                "N",
                "S",
                "P",
                "E",
                "N",
                "D"
            ],
            "layout": [
                0,
                1,
                1,
                1,
                0,
                1,
                1,
                1,
                1,
                1,
                1,
                1,
                1,
                1,
                1,
                1,
                1,
                1,
                1,
                1,
                1,
                1,
                1,
                1,
                1
            ]
        }
    }
]