[
    {
        "puzzle_id": 24207,
        "promo_id": null,
        "version": 3,
        "puzzle_meta": {
            "formatType": "Normal",
            "publishType": "Daily",
            "title": "The Mini Crossword",
            "printDate": "2026-06-30",
            "printDotw": 0,
            "editor": "Joel Fagliano",
            "height": 5,
            "width": 5,
            "author": "Ian Livengood"
        },
        "print_date": "2026-06-30",
        "enhanced_tier_date": null,
        "puzzle_data": {
            "clues": {
                "A": [
                    {
                        "clueStart": 1,
                        "clueNum": 1,
                        "clueEnd": 4,
                        "value": "Big party"
                    },
                    {
                        "clueStart": 5,
                        "clueNum": 5,
                        "clueEnd": 9,
                        "value": "Pricey variety of beef that translates to \"Japanese cow\""
                    },
                    {
                        "clueStart": 10,
                        "clueNum": 6,
                        "clueEnd": 14,
                        "value": "Unwelcome sound at 7 a.m., perhaps"
                    },
                    {
                        "clueStart": 15,
                        "clueNum": 7,
                        "clueEnd": 19,
                        "value": "Really make excited"
                    },
                    {
                        "clueStart": 20,
                        "clueNum": 8,
                        "clueEnd": 23,
                        "value": "Get ready (for)"
                    }
                ],
                "D": [
                    {
                        "clueStart": 1,
                        "clueNum": 1,
                        "clueEnd": 21,
                        "value": "Farm machine that bundles hay"
                    },
                    {
                        "clueStart": 2,
                        "clueNum": 2,
                        "clueEnd": 22,
                        "value": "Plant used to make mezcal"
                    },
                    {
                        "clueStart": 3,
                        "clueNum": 3,
                        "clueEnd": 23,
                        "value": "Pancake topper"
                    },
                    {
                        "clueStart": 4,
                        "clueNum": 4,
                        "clueEnd": 19,
                        "value": "Prominent feature of a camel"
                    },
                    {
                        "clueStart": 5,
                        "clueNum": 5,
                        "clueEnd": 20,
                        "value": "Bend out of shape, as wood"
                    }
                ]
            },
            "answers": [
                null,
                "B",
                "A",
                "S",
                "H",
                "W",
                "A",
                "G",
                "Y",
                "U",
                "A",
                "L",
                "A",
                "R",
                "M",
                "R",
                "E",
                "V",
                "U",
                "P",
                "P",
                "R",
                "E",
                "P",
                null
            ],
            "layout": [
                0,
                1,
                1,
                1,
                1,
                1,
                1,
                1,
                1,
                1,
                1,
                1,
                1,
                1,
                1,
                1,
                1,
                1,
                1,
                1,
                1,
                1,
                1,
                1,
                0
            ]
        }
    }
]