[
    {
        "puzzle_id": 12973,
        "promo_id": null,
        "version": 3,
        "puzzle_meta": {
            "formatType": "Normal",
            "publishType": "Daily",
            "title": "The Mini Crossword",
            "printDate": "2017-03-02",
            "printDotw": 0,
            "editor": "",
            "height": 5,
            "width": 5,
            "author": "Joel Fagliano"
        },
        "print_date": "2017-03-02",
        "enhanced_tier_date": null,
        "puzzle_data": {
            "clues": {
                "A": [
                    {
                        "clueStart": 1,
                        "clueNum": 1,
                        "clueEnd": 4,
                        "value": "Tiny whirlpool"
                    },
                    {
                        "clueStart": 6,
                        "clueNum": 5,
                        "clueEnd": 9,
                        "value": "With 6-Across, guarantee of the First Amendment"
                    },
                    {
                        "clueStart": 10,
                        "clueNum": 6,
                        "clueEnd": 14,
                        "value": "See 5-Across"
                    },
                    {
                        "clueStart": 15,
                        "clueNum": 7,
                        "clueEnd": 18,
                        "value": "Half of a clothing pair"
                    },
                    {
                        "clueStart": 20,
                        "clueNum": 8,
                        "clueEnd": 23,
                        "value": "Fluids in pens"
                    }
                ],
                "D": [
                    {
                        "clueStart": 1,
                        "clueNum": 1,
                        "clueEnd": 21,
                        "value": "Zac of \"Dirty Grandpa\""
                    },
                    {
                        "clueStart": 2,
                        "clueNum": 2,
                        "clueEnd": 22,
                        "value": "Worthless stuff"
                    },
                    {
                        "clueStart": 3,
                        "clueNum": 3,
                        "clueEnd": 23,
                        "value": "Furniture in a school classroom"
                    },
                    {
                        "clueStart": 4,
                        "clueNum": 4,
                        "clueEnd": 14,
                        "value": "\"Signs point to ___\" (Magic 8 Ball answer)"
                    },
                    {
                        "clueStart": 10,
                        "clueNum": 6,
                        "clueEnd": 20,
                        "value": "Letter before omega"
                    }
                ]
            },
            "answers": [
                null,
                "E",
                "D",
                "D",
                "Y",
                null,
                "F",
                "R",
                "E",
                "E",
                "P",
                "R",
                "E",
                "S",
                "S",
                "S",
                "O",
                "C",
                "K",
                null,
                "I",
                "N",
                "K",
                "S",
                null
            ],
            "layout": [
                0,
                1,
                1,
                1,
                1,
                0,
                1,
                1,
                1,
                1,
                1,
                1,
                1,
                1,
                1,
                1,
                1,
                1,
                1,
                0,
                1,
                1,
                1,
                1,
                0
            ]
        }
    }
]