[
    {
        "puzzle_id": 18836,
        "promo_id": null,
        "version": 3,
        "puzzle_meta": {
            "formatType": "Normal",
            "publishType": "Daily",
            "title": "The Mini Crossword",
            "printDate": "2020-12-10",
            "printDotw": 0,
            "editor": "",
            "height": 5,
            "width": 5,
            "author": "Joel Fagliano"
        },
        "print_date": "2020-12-10",
        "enhanced_tier_date": null,
        "puzzle_data": {
            "clues": {
                "A": [
                    {
                        "clueStart": 1,
                        "clueNum": 1,
                        "clueEnd": 4,
                        "value": "Move like a dreidel"
                    },
                    {
                        "clueStart": 6,
                        "clueNum": 5,
                        "clueEnd": 9,
                        "value": "Scent of a Christmas candle"
                    },
                    {
                        "clueStart": 10,
                        "clueNum": 6,
                        "clueEnd": 14,
                        "value": "Grape with \"noir\" and \"grigio\" varieties"
                    },
                    {
                        "clueStart": 15,
                        "clueNum": 7,
                        "clueEnd": 18,
                        "value": "Against"
                    },
                    {
                        "clueStart": 20,
                        "clueNum": 8,
                        "clueEnd": 23,
                        "value": "Give someone a hand"
                    }
                ],
                "D": [
                    {
                        "clueStart": 1,
                        "clueNum": 1,
                        "clueEnd": 21,
                        "value": "Prickly part of a cactus"
                    },
                    {
                        "clueStart": 2,
                        "clueNum": 2,
                        "clueEnd": 22,
                        "value": "Companion of the Ni\u221a\u00b1a and the Santa Maria"
                    },
                    {
                        "clueStart": 3,
                        "clueNum": 3,
                        "clueEnd": 23,
                        "value": "How latkes are cooked"
                    },
                    {
                        "clueStart": 4,
                        "clueNum": 4,
                        "clueEnd": 14,
                        "value": "Nothing but ___"
                    },
                    {
                        "clueStart": 10,
                        "clueNum": 6,
                        "clueEnd": 20,
                        "value": "Bottom of a paw"
                    }
                ]
            },
            "answers": [
                null,
                "S",
                "P",
                "I",
                "N",
                null,
                "P",
                "I",
                "N",
                "E",
                "P",
                "I",
                "N",
                "O",
                "T",
                "A",
                "N",
                "T",
                "I",
                null,
                "D",
                "E",
                "A",
                "L",
                null
            ],
            "layout": [
                0,
                1,
                1,
                1,
                1,
                0,
                1,
                1,
                1,
                1,
                1,
                1,
                1,
                1,
                1,
                1,
                1,
                1,
                1,
                0,
                1,
                1,
                1,
                1,
                0
            ]
        }
    }
]