[
    {
        "puzzle_id": 22022,
        "promo_id": null,
        "version": 3,
        "puzzle_meta": {
            "formatType": "Normal",
            "publishType": "Daily",
            "title": "The Mini Crossword",
            "printDate": "2024-06-06",
            "printDotw": 0,
            "editor": "Sam Ezersky",
            "height": 5,
            "width": 5,
            "author": "Christina Iverson"
        },
        "print_date": "2024-06-06",
        "enhanced_tier_date": null,
        "puzzle_data": {
            "clues": {
                "A": [
                    {
                        "clueStart": 1,
                        "clueNum": 1,
                        "clueEnd": 4,
                        "value": "Good way to get in shape \u2026 in more than one way"
                    },
                    {
                        "clueStart": 5,
                        "clueNum": 5,
                        "clueEnd": 9,
                        "value": "British nobility title"
                    },
                    {
                        "clueStart": 10,
                        "clueNum": 6,
                        "clueEnd": 14,
                        "value": "\"Heaven help us!\""
                    },
                    {
                        "clueStart": 15,
                        "clueNum": 7,
                        "clueEnd": 18,
                        "value": "What a cat resembles when it sits with its legs tucked under its body"
                    },
                    {
                        "clueStart": 20,
                        "clueNum": 8,
                        "clueEnd": 22,
                        "value": "\"___ Quixote\" (Cervantes epic)"
                    }
                ],
                "D": [
                    {
                        "clueStart": 1,
                        "clueNum": 1,
                        "clueEnd": 21,
                        "value": "Google alternative"
                    },
                    {
                        "clueStart": 2,
                        "clueNum": 2,
                        "clueEnd": 22,
                        "value": "Instrument at a basilica or a baseball stadium"
                    },
                    {
                        "clueStart": 3,
                        "clueNum": 3,
                        "clueEnd": 18,
                        "value": "Silly mistake"
                    },
                    {
                        "clueStart": 4,
                        "clueNum": 4,
                        "clueEnd": 14,
                        "value": "\"Your point is \u2026?\""
                    },
                    {
                        "clueStart": 5,
                        "clueNum": 5,
                        "clueEnd": 20,
                        "value": "Like this text"
                    }
                ]
            },
            "answers": [
                null,
                "Y",
                "O",
                "G",
                "A",
                "B",
                "A",
                "R",
                "O",
                "N",
                "O",
                "H",
                "G",
                "O",
                "D",
                "L",
                "O",
                "A",
                "F",
                null,
                "D",
                "O",
                "N",
                null,
                null
            ],
            "layout": [
                0,
                1,
                1,
                1,
                1,
                1,
                1,
                1,
                1,
                1,
                1,
                1,
                1,
                1,
                1,
                1,
                1,
                1,
                1,
                0,
                1,
                1,
                1,
                0,
                0
            ]
        }
    }
]