[
    {
        "puzzle_id": 23292,
        "promo_id": null,
        "version": 3,
        "puzzle_meta": {
            "formatType": "Normal",
            "publishType": "Daily",
            "title": "The Mini Crossword",
            "printDate": "2025-11-03",
            "printDotw": 0,
            "editor": "",
            "height": 5,
            "width": 5,
            "author": "Joel Fagliano"
        },
        "print_date": "2025-11-03",
        "enhanced_tier_date": null,
        "puzzle_data": {
            "clues": {
                "A": [
                    {
                        "clueStart": 0,
                        "clueNum": 1,
                        "clueEnd": 3,
                        "value": "On the ___ (using Tinder or Bumble)"
                    },
                    {
                        "clueStart": 5,
                        "clueNum": 5,
                        "clueEnd": 8,
                        "value": "Color of the second-hardest Connections category"
                    },
                    {
                        "clueStart": 10,
                        "clueNum": 6,
                        "clueEnd": 14,
                        "value": "Prepare, as a Thanksgiving turkey"
                    },
                    {
                        "clueStart": 16,
                        "clueNum": 8,
                        "clueEnd": 19,
                        "value": "Have to have"
                    },
                    {
                        "clueStart": 21,
                        "clueNum": 9,
                        "clueEnd": 24,
                        "value": "Camper's construction"
                    }
                ],
                "D": [
                    {
                        "clueStart": 0,
                        "clueNum": 1,
                        "clueEnd": 10,
                        "value": "Kimmel's channel"
                    },
                    {
                        "clueStart": 1,
                        "clueNum": 2,
                        "clueEnd": 21,
                        "value": "Audience member who's in on the magic trick"
                    },
                    {
                        "clueStart": 2,
                        "clueNum": 3,
                        "clueEnd": 22,
                        "value": "Many a baby food"
                    },
                    {
                        "clueStart": 3,
                        "clueNum": 4,
                        "clueEnd": 23,
                        "value": "Typical number of objects that humans can hold in working memory, hence phone numbers"
                    },
                    {
                        "clueStart": 14,
                        "clueNum": 7,
                        "clueEnd": 24,
                        "value": "Summer hrs. in N.Y.C."
                    }
                ]
            },
            "answers": [
                "A",
                "P",
                "P",
                "S",
                null,
                "B",
                "L",
                "U",
                "E",
                null,
                "C",
                "A",
                "R",
                "V",
                "E",
                null,
                "N",
                "E",
                "E",
                "D",
                null,
                "T",
                "E",
                "N",
                "T"
            ],
            "layout": [
                1,
                1,
                1,
                1,
                0,
                1,
                1,
                1,
                1,
                0,
                1,
                1,
                1,
                1,
                1,
                0,
                1,
                1,
                1,
                1,
                0,
                1,
                1,
                1,
                1
            ]
        }
    }
]