[
    {
        "puzzle_id": 16280,
        "promo_id": null,
        "version": 3,
        "puzzle_meta": {
            "formatType": "Normal",
            "publishType": "Daily",
            "title": "The Mini Crossword",
            "printDate": "2019-01-28",
            "printDotw": 0,
            "editor": "",
            "height": 5,
            "width": 5,
            "author": "Joel Fagliano"
        },
        "print_date": "2019-01-28",
        "enhanced_tier_date": null,
        "puzzle_data": {
            "clues": {
                "A": [
                    {
                        "clueStart": 0,
                        "clueNum": 1,
                        "clueEnd": 3,
                        "value": "First man"
                    },
                    {
                        "clueStart": 5,
                        "clueNum": 5,
                        "clueEnd": 8,
                        "value": "Law for \"dreamers,\" for short"
                    },
                    {
                        "clueStart": 10,
                        "clueNum": 6,
                        "clueEnd": 14,
                        "value": "Taters"
                    },
                    {
                        "clueStart": 16,
                        "clueNum": 8,
                        "clueEnd": 19,
                        "value": "Salt Lake City's state"
                    },
                    {
                        "clueStart": 21,
                        "clueNum": 9,
                        "clueEnd": 24,
                        "value": "___ Buttigieg, mayor running for the 2020 Democratic nomination"
                    }
                ],
                "D": [
                    {
                        "clueStart": 0,
                        "clueNum": 1,
                        "clueEnd": 10,
                        "value": "First few minutes of most podcasts"
                    },
                    {
                        "clueStart": 1,
                        "clueNum": 2,
                        "clueEnd": 21,
                        "value": "Give a fist bump to, slangily"
                    },
                    {
                        "clueStart": 2,
                        "clueNum": 3,
                        "clueEnd": 22,
                        "value": "Less than 90\u00c2\u00b0, as an angle"
                    },
                    {
                        "clueStart": 3,
                        "clueNum": 4,
                        "clueEnd": 23,
                        "value": "Angry with"
                    },
                    {
                        "clueStart": 14,
                        "clueNum": 7,
                        "clueEnd": 24,
                        "value": "That woman"
                    }
                ]
            },
            "answers": [
                "A",
                "D",
                "A",
                "M",
                null,
                "D",
                "A",
                "C",
                "A",
                null,
                "S",
                "P",
                "U",
                "D",
                "S",
                null,
                "U",
                "T",
                "A",
                "H",
                null,
                "P",
                "E",
                "T",
                "E"
            ],
            "layout": [
                1,
                1,
                1,
                1,
                0,
                1,
                1,
                1,
                1,
                0,
                1,
                1,
                1,
                1,
                1,
                0,
                1,
                1,
                1,
                1,
                0,
                1,
                1,
                1,
                1
            ]
        }
    }
]