[
    {
        "puzzle_id": 18459,
        "promo_id": null,
        "version": 3,
        "puzzle_meta": {
            "formatType": "Normal",
            "publishType": "Daily",
            "title": "The Mini Crossword",
            "printDate": "2020-07-22",
            "printDotw": 0,
            "editor": "",
            "height": 5,
            "width": 5,
            "author": "Joel Fagliano"
        },
        "print_date": "2020-07-22",
        "enhanced_tier_date": null,
        "puzzle_data": {
            "clues": {
                "A": [
                    {
                        "clueStart": 2,
                        "clueNum": 1,
                        "clueEnd": 4,
                        "value": "Like fish in poke"
                    },
                    {
                        "clueStart": 5,
                        "clueNum": 4,
                        "clueEnd": 9,
                        "value": "Texas landmark to \"remember\""
                    },
                    {
                        "clueStart": 10,
                        "clueNum": 6,
                        "clueEnd": 14,
                        "value": "Boggle accessory"
                    },
                    {
                        "clueStart": 15,
                        "clueNum": 7,
                        "clueEnd": 19,
                        "value": "Standing upright, as a box"
                    },
                    {
                        "clueStart": 20,
                        "clueNum": 8,
                        "clueEnd": 22,
                        "value": "\"___ and the Art of Motorcycle Maintenance\" (1974 best-selling book)"
                    }
                ],
                "D": [
                    {
                        "clueStart": 2,
                        "clueNum": 1,
                        "clueEnd": 22,
                        "value": "Soup served with chopsticks"
                    },
                    {
                        "clueStart": 3,
                        "clueNum": 2,
                        "clueEnd": 18,
                        "value": "\"Preach!\""
                    },
                    {
                        "clueStart": 4,
                        "clueNum": 3,
                        "clueEnd": 19,
                        "value": "Scrabble play"
                    },
                    {
                        "clueStart": 5,
                        "clueNum": 4,
                        "clueEnd": 20,
                        "value": "Dictionary order"
                    },
                    {
                        "clueStart": 6,
                        "clueNum": 5,
                        "clueEnd": 21,
                        "value": "Infinite series of points"
                    }
                ]
            },
            "answers": [
                null,
                null,
                "R",
                "A",
                "W",
                "A",
                "L",
                "A",
                "M",
                "O",
                "T",
                "I",
                "M",
                "E",
                "R",
                "O",
                "N",
                "E",
                "N",
                "D",
                "Z",
                "E",
                "N",
                null,
                null
            ],
            "layout": [
                0,
                0,
                1,
                1,
                1,
                1,
                1,
                1,
                1,
                1,
                1,
                1,
                1,
                1,
                1,
                1,
                1,
                1,
                1,
                1,
                1,
                1,
                1,
                0,
                0
            ]
        }
    }
]