[
    {
        "puzzle_id": 21390,
        "promo_id": null,
        "version": 3,
        "puzzle_meta": {
            "formatType": "Normal",
            "publishType": "Daily",
            "title": "The Mini Crossword",
            "printDate": "2023-08-28",
            "printDotw": 0,
            "editor": "",
            "height": 5,
            "width": 5,
            "author": "Joel Fagliano"
        },
        "print_date": "2023-08-28",
        "enhanced_tier_date": null,
        "puzzle_data": {
            "clues": {
                "A": [
                    {
                        "clueStart": 1,
                        "clueNum": 1,
                        "clueEnd": 4,
                        "value": "Gusted ... or a homophone of a primary color"
                    },
                    {
                        "clueStart": 6,
                        "clueNum": 5,
                        "clueEnd": 9,
                        "value": "Interpreted ... or a homophone of a primary color"
                    },
                    {
                        "clueStart": 10,
                        "clueNum": 6,
                        "clueEnd": 14,
                        "value": "Dinghies and other such thingies"
                    },
                    {
                        "clueStart": 15,
                        "clueNum": 7,
                        "clueEnd": 18,
                        "value": "Turn in chess"
                    },
                    {
                        "clueStart": 20,
                        "clueNum": 8,
                        "clueEnd": 23,
                        "value": "Wolverine and Cyclops, in the Marvel universe"
                    }
                ],
                "D": [
                    {
                        "clueStart": 1,
                        "clueNum": 1,
                        "clueEnd": 21,
                        "value": "Witch's ride"
                    },
                    {
                        "clueStart": 2,
                        "clueNum": 2,
                        "clueEnd": 22,
                        "value": "Head out"
                    },
                    {
                        "clueStart": 3,
                        "clueNum": 3,
                        "clueEnd": 23,
                        "value": "Consumed"
                    },
                    {
                        "clueStart": 4,
                        "clueNum": 4,
                        "clueEnd": 14,
                        "value": "Dictionary entries: Abbr."
                    },
                    {
                        "clueStart": 10,
                        "clueNum": 6,
                        "clueEnd": 20,
                        "value": "Sport with stunt bikes, for short"
                    }
                ]
            },
            "answers": [
                null,
                "B",
                "L",
                "E",
                "W",
                null,
                "R",
                "E",
                "A",
                "D",
                "B",
                "O",
                "A",
                "T",
                "S",
                "M",
                "O",
                "V",
                "E",
                null,
                "X",
                "M",
                "E",
                "N",
                null
            ],
            "layout": [
                0,
                1,
                1,
                1,
                1,
                0,
                1,
                1,
                1,
                1,
                1,
                1,
                1,
                1,
                1,
                1,
                1,
                1,
                1,
                0,
                1,
                1,
                1,
                1,
                0
            ]
        }
    }
]