[
    {
        "puzzle_id": 21693,
        "promo_id": null,
        "version": 3,
        "puzzle_meta": {
            "formatType": "Normal",
            "publishType": "Daily",
            "title": "The Mini Crossword",
            "printDate": "2024-01-17",
            "printDotw": 0,
            "editor": "",
            "height": 5,
            "width": 5,
            "author": "Joel Fagliano"
        },
        "print_date": "2024-01-17",
        "enhanced_tier_date": null,
        "puzzle_data": {
            "clues": {
                "A": [
                    {
                        "clueStart": 1,
                        "clueNum": 1,
                        "clueEnd": 4,
                        "value": "Director Guillermo del ___"
                    },
                    {
                        "clueStart": 6,
                        "clueNum": 5,
                        "clueEnd": 9,
                        "value": "\"Put ___ in it,\" advice for solving four answers in this puzzle"
                    },
                    {
                        "clueStart": 10,
                        "clueNum": 6,
                        "clueEnd": 14,
                        "value": "Backbone"
                    },
                    {
                        "clueStart": 15,
                        "clueNum": 7,
                        "clueEnd": 18,
                        "value": "Sound of a Slack message"
                    },
                    {
                        "clueStart": 20,
                        "clueNum": 8,
                        "clueEnd": 23,
                        "value": "Greek god of war"
                    }
                ],
                "D": [
                    {
                        "clueStart": 1,
                        "clueNum": 1,
                        "clueEnd": 21,
                        "value": "Animal that looks like an elephant/pig hybrid"
                    },
                    {
                        "clueStart": 2,
                        "clueNum": 2,
                        "clueEnd": 22,
                        "value": "Offer a viewpoint"
                    },
                    {
                        "clueStart": 3,
                        "clueNum": 3,
                        "clueEnd": 23,
                        "value": "Parts of the Olympics logo"
                    },
                    {
                        "clueStart": 4,
                        "clueNum": 4,
                        "clueEnd": 14,
                        "value": "Number of stars on Puerto Rico's flag"
                    },
                    {
                        "clueStart": 10,
                        "clueNum": 6,
                        "clueEnd": 20,
                        "value": "Place to get a massage"
                    }
                ]
            },
            "answers": [
                null,
                "T",
                "O",
                "R",
                "O",
                null,
                "A",
                "P",
                "I",
                "N",
                "S",
                "P",
                "I",
                "N",
                "E",
                "P",
                "I",
                "N",
                "G",
                null,
                "A",
                "R",
                "E",
                "S",
                null
            ],
            "layout": [
                0,
                1,
                1,
                1,
                1,
                0,
                1,
                1,
                1,
                1,
                1,
                1,
                1,
                1,
                1,
                1,
                1,
                1,
                1,
                0,
                1,
                1,
                1,
                1,
                0
            ]
        }
    }
]